<?xml version="1.0"?>
<schema xmlns:xsi="http://www.w3.org/2001/XMLSchema-instance" xsi:noNamespaceSchemaLocation="urn:magento:framework:Setup/Declaration/Schema/etc/schema.xsd">
    <table name="macademy_minerva_faq" engine="innodb" comment="FAQs">
        <column name="id" xsi:type="int" padding="10" unsigned="true" nullable="false" identity="true" comment="Id"/>
        <column name="question" xsi:type="text" nullable="false" comment="Question"/>
        <column name="answer" xsi:type="text" nullable="false" comment="Answer"/>
        <column name="is_published" xsi:type="boolean" nullable="false" default="false" comment="Is published"/>
        <column name="created_at" xsi:type="datetime" nullable="false" default="CURRENT_TIMESTAMP" on_update="false" comment="Created at"/>
        <column name="updated_at" xsi:type="datetime" nullable="false" default="CURRENT_TIMESTAMP" on_update="true" comment="Updated at"/>
        <constraint xsi:type="primary" referenceId="PRIMARY">
            <column name="id"/>
        </constraint>
        <index referenceId="MACADEMY_MINERVA_FAQ_QUESTION" indexType="fulltext">
            <column name="question"/>
        </index>
    </table>
</schema>
